setup.cfg
setup.py
quantumworld/__init__.py
quantumworld/quantumworld.py
quantumworld.egg-info/PKG-INFO
quantumworld.egg-info/SOURCES.txt
quantumworld.egg-info/dependency_links.txt
quantumworld.egg-info/requires.txt
quantumworld.egg-info/top_level.txt