Metadata-Version: 1.0
Name: quantumworld
Version: 1.0b0
Summary: Basic library for the QuantumWorldX course
Home-page: UNKNOWN
Author: Benjamin Sanchez Lengeling
Author-email: beangoben@gmail.com
License: MIT
Keywords: Quantum Chemistry,edX,Quantum Mechanics
Platform: UNKNOWN
